LICENSE.txt
README.md
setup.cfg
setup.py
omrdatasettools/AudiverisOmrImageGenerator.py
omrdatasettools/CapitanImageGenerator.py
omrdatasettools/Downloader.py
omrdatasettools/ExportPath.py
omrdatasettools/HomusImageGenerator.py
omrdatasettools/MeasureVisualizer.py
omrdatasettools/MuscimaPlusPlusMaskImageGenerator.py
omrdatasettools/MuscimaPlusPlusSymbolImageGenerator.py
omrdatasettools/OmrDataset.py
omrdatasettools/Point2D.py
omrdatasettools/Rectangle.py
omrdatasettools/__init__.py
omrdatasettools/_version.py
omrdatasettools.egg-info/PKG-INFO
omrdatasettools.egg-info/SOURCES.txt
omrdatasettools.egg-info/dependency_links.txt
omrdatasettools.egg-info/requires.txt
omrdatasettools.egg-info/top_level.txt
omrdatasettools/tests/__init__.py
omrdatasettools/tests/test_audiveris_image_generator.py
omrdatasettools/tests/test_capitan_image_generator.py
omrdatasettools/tests/test_capitan_symbol.py
omrdatasettools/tests/test_downloader.py
omrdatasettools/tests/test_export_path.py
omrdatasettools/tests/test_homus_image_generator.py
omrdatasettools/tests/test_homus_symbol.py
omrdatasettools/tests/test_muscima_pp_mask_image_generator.py
omrdatasettools/tests/test_muscima_pp_symbol_image_generator.py