Metadata-Version: 2.1
Name: omrdatasettools
Version: 1.4.0
Summary: A collection of tools that simplify the downloading and handling of datasets used for Optical Music Recognition (OMR).
Home-page: https://github.com/apacha/omr-datasets
Download-URL: https://github.com/apacha/OMR-Datasets/archive/1.4.0.tar.gz
Author: Alexander Pacha
Author-email: alexander.pacha@tuwien.ac.at
License: MIT
Keywords: optical music recognition,downloading,extracting,omr,generating,dataset,preprocessing
Classifier: Development Status :: 5 - Production/Stable
Classifier: Intended Audience :: Developers
Classifier: Intended Audience :: Science/Research
Classifier: Topic :: Scientific/Engineering :: Image Recognition
Classifier: Topic :: Scientific/Engineering :: Visualization
Classifier: Topic :: Multimedia :: Graphics
Classifier: License :: OSI Approved :: MIT License
Classifier: Programming Language :: Python :: 3
Classifier: Programming Language :: Python :: 3.8
Classifier: Programming Language :: Python :: 3.9
Classifier: Programming Language :: Python :: 3.10
Classifier: Programming Language :: Python :: 3.11
License-File: LICENSE.txt
Requires-Dist: Pillow
Requires-Dist: muscima
Requires-Dist: mung
Requires-Dist: numpy
Requires-Dist: tqdm
Requires-Dist: scikit-image
Requires-Dist: lxml
